uun_weatherstation/__init__.py
uun_weatherstation/diagnostic.py
uun_weatherstation/utils.py
uun_weatherstation/data/sample-config.json
uun_weatherstation/data/start.sh
uun_weatherstation/data/systemd.service
uun_weatherstation/modules/HealthCheck.py
uun_weatherstation/modules/WeatherConditions.py
uun_weatherstation/modules/__init__.py
uun_weatherstation-0.6.10.data/scripts/uun-weatherstation
uun_weatherstation-0.6.10.data/scripts/uun-weatherstation-install
uun_weatherstation-0.6.10.dist-info/LICENSE.md
uun_weatherstation-0.6.10.dist-info/METADATA
uun_weatherstation-0.6.10.dist-info/WHEEL
uun_weatherstation-0.6.10.dist-info/top_level.txt
uun_weatherstation-0.6.10.dist-info/RECORD
