Metadata-Version: 2.1
Name: uun-weatherstation
Version: 0.6.10
Summary: Get weather conditions from WeatherLink and send them to uuApp.
Home-page: https://uuos9.plus4u.net/uu-bookkitg01-main/c145b7fe6d754775b71e196b3fbb9a6a/book/page?code=home
Author: (UUN) Tomáš Faikl
Author-email: tomas.faikl@unicornuniversity.net
Classifier: Programming Language :: Python :: 3
Classifier: License :: OSI Approved :: MIT License
Requires-Python: >=3.6
License-File: LICENSE.md
Requires-Dist: uun-iot >=0.10.0
Requires-Dist: requests >=2.24.0
